pyfission/__init__.py
pyfission/__main__.py
pyfission/sync.py
pyfission/configs/__init__.py
pyfission/configs/config.py
pyfission/configs/custom_config.py
pyfission/configs/fission.py
pyfission/configs/schema_mapper.py
pyfission/custom_logging/__init__.py
pyfission/custom_logging/__main__.py
pyfission/logs/__init__.py
pyfission/secrets_storage/__init__.py
pyfission/sql/__init__.py
pyfission/sql/bigquery/__init__.py
pyfission/sql/bigquery/bq_load_table_generic.sql
pyfission/sql/bigquery/bq_load_table_generic_drop_only.sql
pyfission/sql/bigquery/delete_all_records.sql
pyfission/sql/bigquery/delete_from_table.sql
pyfission/sql/bigquery/delete_from_table_join.sql
pyfission/sql/bigquery/drop_table.sql
pyfission/sql/mysql/__init__.py
pyfission/sql/mysql/delete_all_records.sql
pyfission/sql/mysql/drop_table.sql
pyfission/sql/redshift/__init__.py
pyfission/sql/redshift/delete_all_records.sql
pyfission/sql/redshift/drop_table.sql
pyfission/sql/redshift/raw_to_main.sql
pyfission/sql/redshift/raw_to_main_truncate.sql
pyfission/sql/redshift/s3_to_redshift.sql
pyfission/sql/redshift/s3_to_redshift_json.sql
pyfission/storage/__init__.py
pyfission/utils/__init__.py
pyfission/utils/cloud_google.py
pyfission/utils/database.py
pyfission/utils/file.py
pyfission/utils/s3_util.py
pyfission/utils/util.py
pyfission/utils/worker.py
pyFission-1.0.2.dist-info/LICENSE.md
pyFission-1.0.2.dist-info/METADATA
pyFission-1.0.2.dist-info/WHEEL
pyFission-1.0.2.dist-info/top_level.txt
pyFission-1.0.2.dist-info/RECORD
