Metadata-Version: 2.1
Name: pyFission
Version: 1.0.2
Summary: A tool to sync data across data sources
Home-page: https://github.com/nishantnath/pyfission/
Author: Nishant Nath, Aniket Shenoy
License: MIT
Platform: UNKNOWN
Requires-Dist: google-cloud-storage
Requires-Dist: google-cloud-bigquery
Requires-Dist: pandas-gbq
Requires-Dist: pandas
Requires-Dist: sqlalchemy
Requires-Dist: pymysql
Requires-Dist: pymssql
Requires-Dist: pyodbc
Requires-Dist: cx-Oracle
Requires-Dist: boto3
